tcellmatch/__init__.py
tcellmatch/_version.py
tcellmatch-0.1.0.dist-info/LICENSE
tcellmatch-0.1.0.dist-info/METADATA
tcellmatch-0.1.0.dist-info/WHEEL
tcellmatch-0.1.0.dist-info/top_level.txt
tcellmatch-0.1.0.dist-info/RECORD
